__init__.py
WidgetCollection/__init__.py
WidgetCollection/Dialogs/AboutDialog.py
WidgetCollection/Dialogs/__init__.py
WidgetCollection/Tools/PyProjectExtractor.py
WidgetCollection/Tools/__init__.py
WidgetCollection/widgets/LEDIndicatorWidget.py
WidgetCollection/widgets/PlayPushButton.py
WidgetCollection/widgets/QProgressBarWindow.py
WidgetCollection/widgets/__init__.py
PySide6WidgetCollection-1.0.3.dist-info/LICENSE
PySide6WidgetCollection-1.0.3.dist-info/METADATA
PySide6WidgetCollection-1.0.3.dist-info/WHEEL
PySide6WidgetCollection-1.0.3.dist-info/top_level.txt
PySide6WidgetCollection-1.0.3.dist-info/RECORD
