Metadata-Version: 2.1
Name: PySide6WidgetCollection
Version: 1.0.3
Summary: A collection of widgets and tools for PySide6 Applications
Author-email: Christoph Schmidt <cschmidt.fs@gmail.com>
Project-URL: Homepage, https://github.com/agentsmith29/PySide6WidgetCollection
Classifier: Programming Language :: Python :: 3
Classifier: License :: OSI Approved :: GNU General Public License v3 (GPLv3)
Classifier: Operating System :: OS Independent
Requires-Python: >=3.7
License-File: LICENSE
Requires-Dist: pyside6
Requires-Dist: rich
Requires-Dist: pyyaml
Requires-Dist: toml
